  <teiCorpus xmlns="http://www.tei-c.org/ns/1.0">
<teiHeader>
    <fileDesc>
                <titleStmt>
            <title>Catalogo Cicognara Number 1009</title>
        </titleStmt>
        <publicationStmt>
            <publisher>
               <orgName>Digital Cicognara Library</orgName>
               <ref>https://cicognara.org</ref>
            </publisher>
            <sectionNumber>1.11</sectionNumber>
            <idno type="cico">1009</idno>
        </publicationStmt>
        <sourceDesc>
            <bibl><author>BONARROTI Michelangelo</author>, <title>Rime raccolte da Michelangelo suo nipote</title>, <pubPlace>Firenze</pubPlace>, presso <publisher>i
      Giunti</publisher>, <date>1623</date>, in 4, piccolo.
      </bibl>
        </sourceDesc>
    </fileDesc>
</teiHeader>
        
</teiCorpus>
