  <teiCorpus xmlns="http://www.tei-c.org/ns/1.0">
<teiHeader>
    <fileDesc>
                <titleStmt>
            <title>Catalogo Cicognara Number 1125</title>
        </titleStmt>
        <publicationStmt>
            <publisher>
               <orgName>Digital Cicognara Library</orgName>
               <ref>https://cicognara.org</ref>
            </publisher>
            <sectionNumber>1.14</sectionNumber>
            <idno type="cico">1125</idno>
        </publicationStmt>
        <sourceDesc>
            <bibl><author>De la FONTAINE</author>, <title>Fables choisies en vers par de la Fontaine</title>, 4 vol. in fol. fig., <pubPlace>Paris</pubPlace> <date>1755 al
  1759</date>.
  <note>Le tavole sono disegnate da Oudry e incise da parecchi de’ migliori incisori di quel tempo col ritratto di Oudry in
  principio.</note>
  
  </bibl>
        </sourceDesc>
    </fileDesc>
</teiHeader>
        
</teiCorpus>
