  <teiCorpus xmlns="http://www.tei-c.org/ns/1.0">
<teiHeader>
    <fileDesc>
                <titleStmt>
            <title>Catalogo Cicognara Number 1323</title>
        </titleStmt>
        <publicationStmt>
            <publisher>
               <orgName>Digital Cicognara Library</orgName>
               <ref>https://cicognara.org</ref>
            </publisher>
            <sectionNumber>1.17</sectionNumber>
            <idno type="cico">1323</idno>
        </publicationStmt>
        <sourceDesc>
            <bibl><author>GUATTANI Giuseppe Antonio</author>, <title>Monumenti antichi inediti, ovvero notizie sulle antichità e
    belle Arti di Roma</title>, vol. 6, legati in 3.
    <note>Comincia nell’anno <date>1784</date> e finisce col <date>1789</date>,</note> <pubPlace>Roma</pubPlace><note> in 4, fig.</note>
    
    </bibl>
        </sourceDesc>
    </fileDesc>
</teiHeader>
        
</teiCorpus>
