  <teiCorpus xmlns="http://www.tei-c.org/ns/1.0">
<teiHeader>
    <fileDesc>
                <titleStmt>
            <title>Catalogo Cicognara Number 1484</title>
        </titleStmt>
        <publicationStmt>
            <publisher>
               <orgName>Digital Cicognara Library</orgName>
               <ref>https://cicognara.org</ref>
            </publisher>
            <sectionNumber>1.18</sectionNumber>
            <idno type="cico">1484</idno>
        </publicationStmt>
        <sourceDesc>
            <bibl><title>DISEGNI del convito fatto dall’Illustriss. Sig. Francesco Ratta al pubblico ed anziani;
<fw type="foot"/>
                  <pb type="memofonte"/>
                  <fw type="head"/>
    
    terminando il suo gonfalonierato li 28 febb. <date>1693</date></title>, <pubPlace>Bologna</pubPlace>, in fol. fig. con 6 tavole.
    MDCXCIV
    
    </bibl>
        </sourceDesc>
    </fileDesc>
</teiHeader>
        
</teiCorpus>
