  <teiCorpus xmlns="http://www.tei-c.org/ns/1.0">
<teiHeader>
    <fileDesc>
                <titleStmt>
            <title>Catalogo Cicognara Number 1512</title>
        </titleStmt>
        <publicationStmt>
            <publisher>
               <orgName>Digital Cicognara Library</orgName>
               <ref>https://cicognara.org</ref>
            </publisher>
            <sectionNumber>1.18</sectionNumber>
            <idno type="cico">1512</idno>
        </publicationStmt>
        <sourceDesc>
            <bibl><title>RÉLACION de las exequias hechas en Roma a la magestad catolica de Phelippe V</title>, <pubPlace>Roma</pubPlace> <date>1746</date>,
    in foglio, fig.
    <note>Con due orazioni funerali, l’una di Mons. Marcolini, l’altra del Padre Guzman Gesuita. Con sette grandissime
    tavole atlantiche inventate e disegnate dal Cav. Fuga e intagliate da vari artefici.</note>
    MDCCXLVII
    
    </bibl>
        </sourceDesc>
    </fileDesc>
</teiHeader>
        
</teiCorpus>
