  <teiCorpus xmlns="http://www.tei-c.org/ns/1.0">
<teiHeader>
    <fileDesc>
                <titleStmt>
            <title>Catalogo Cicognara Number 1565</title>
        </titleStmt>
        <publicationStmt>
            <publisher>
               <orgName>Digital Cicognara Library</orgName>
               <ref>https://cicognara.org</ref>
            </publisher>
            <sectionNumber>1.20</sectionNumber>
            <idno type="cico">1565</idno>
        </publicationStmt>
        <sourceDesc>
            <bibl><author>BACII Andreae</author>, <title>De thermis libri septem</title>,<pubPlace> Venetiis</pubPlace> 
                     <date>1571</date>, in fol. pic. fig.
    <note>Prima e rara edizione, esemplare bellissimo, secondo la descrizione del de Bure.</note>
    
    </bibl>
        </sourceDesc>
    </fileDesc>
</teiHeader>
        
</teiCorpus>
