  <teiCorpus xmlns="http://www.tei-c.org/ns/1.0">
<teiHeader>
    <fileDesc>
                <titleStmt>
            <title>Catalogo Cicognara Number 1591</title>
        </titleStmt>
        <publicationStmt>
            <publisher>
               <orgName>Digital Cicognara Library</orgName>
               <ref>https://cicognara.org</ref>
            </publisher>
            <sectionNumber>1.20</sectionNumber>
            <idno type="cico">1591</idno>
        </publicationStmt>
        <sourceDesc>
            <bibl><author>BIRINGUCCIO Vannuccio nob. senese</author>, <title>Pirotechnia</title>. Li diece libri della Pirotechnia ove si tratta
    non solo delle miniere ma anche quanto si ricerca nella pratica di esse e di quanto si
    appartiene all’arte della funzione ovver getto de’ metalli ec., in <pubPlace>Venezia</pubPlace>, per <publisher>Gio. Padovano</publisher>,
    <date>1550</date>, in 4, ad istanza di Curzio di Navo.
    <note>Le numerose tavole necessarie a tante dimostrazioni sono stampate in legno fra il testo; e quest’opera non
    comune, specialmente in questa prima edizione, è interessante per la fusione dei metalli e per ogni altra cosa che
    d quella dipende. Dopo il frontespizio figurato, a tergo di cui è la dedica, vengono due foglietti di tavola delle
    materie e cinque foglietti di proemio. Indi seguono 167 foglietti del testo e nell’ultimo è lo stemma di Curzio, la
    tutto 176 foglietti.</note>
    
    </bibl>
        </sourceDesc>
    </fileDesc>
</teiHeader>
        
</teiCorpus>
