  <teiCorpus xmlns="http://www.tei-c.org/ns/1.0">
<teiHeader>
    <fileDesc>
                <titleStmt>
            <title>Catalogo Cicognara Number 1736</title>
        </titleStmt>
        <publicationStmt>
            <publisher>
               <orgName>Digital Cicognara Library</orgName>
               <ref>https://cicognara.org</ref>
            </publisher>
            <sectionNumber>1.20</sectionNumber>
            <idno type="cico">1736</idno>
        </publicationStmt>
        <sourceDesc>
            <bibl><author>OESTERLIHGIUS Jo.</author>, <title>Dissertatio historica de urnis sepulcralibus et armis lapideis veterum
  Cattorum</title>, <pubPlace>Lipsiae</pubPlace> <date>1741</date>, in 4, fig. M. 96.
  <note>Con una tavola intagliata in rame.</note>
  
  </bibl>
        </sourceDesc>
    </fileDesc>
</teiHeader>
        
</teiCorpus>
