  <teiCorpus xmlns="http://www.tei-c.org/ns/1.0">
<teiHeader>
    <fileDesc>
                <titleStmt>
            <title>Catalogo Cicognara Number 2225</title>
        </titleStmt>
        <publicationStmt>
            <publisher>
               <orgName>Digital Cicognara Library</orgName>
               <ref>https://cicognara.org</ref>
            </publisher>
            <sectionNumber>1.25</sectionNumber>
            <idno type="cico">2225</idno>
        </publicationStmt>
        <sourceDesc>
            <bibl><author>CANALI Luigi</author>, <title>Elogio funebre del Sig. Baldassare Orsini, direttore dell Accademia di Belle
    Arti in Perugia</title>, <pubPlace>Perugia</pubPlace> <date>1811</date>, in 8, M. 88.
    <pb type="cico" n="382"/>
               </bibl>
        </sourceDesc>
    </fileDesc>
</teiHeader>
        
</teiCorpus>
