  <teiCorpus xmlns="http://www.tei-c.org/ns/1.0">
<teiHeader>
    <fileDesc>
                <titleStmt>
            <title>Catalogo Cicognara Number 2383</title>
        </titleStmt>
        <publicationStmt>
            <publisher>
               <orgName>Digital Cicognara Library</orgName>
               <ref>https://cicognara.org</ref>
            </publisher>
            <sectionNumber>1.25</sectionNumber>
            <idno type="cico">2383</idno>
        </publicationStmt>
        <sourceDesc>
            <bibl><author>UGHI Luigi</author>, <title>Dizionario storico degli uomini illustri ferraresi, (ove è parlato anche degli
    artisti)</title>, <pubPlace>Ferrara</pubPlace> <date>1814</date>, in 8.
<fw type="foot"/>
                  <pb type="memofonte"/>
                  <fw type="head"/><note>
    Due tomi in un sol volume, che non onorano la patria di tanti uomini insigni in ogni ramo di arti e di lettere.
    </note>
    </bibl>
        </sourceDesc>
    </fileDesc>
</teiHeader>
        
</teiCorpus>
