  <teiCorpus xmlns="http://www.tei-c.org/ns/1.0">
<teiHeader>
    <fileDesc>
                <titleStmt>
            <title>Catalogo Cicognara Number 2458</title>
        </titleStmt>
        <publicationStmt>
            <publisher>
               <orgName>Digital Cicognara Library</orgName>
               <ref>https://cicognara.org</ref>
            </publisher>
            <sectionNumber>1.26</sectionNumber>
            <idno type="cico">2458</idno>
        </publicationStmt>
        <sourceDesc>
            <bibl><author>PORTAE J. Bapt. Neapolitani</author>, <title>Della celeste fisonomia libri sei nei quali, ribattuta la vanità
    dell’astrologia giudiziaria, si da a conoscere per le cause naturali tutto ciò che l’aspetto e le
    fattezze degli uomini possono significare</title>, <pubPlace>Padova</pubPlace> <date>1616</date>, in 4, pic. fig.
    <note>Colle figure in legno fra il testo.</note>
    
    </bibl>
        </sourceDesc>
    </fileDesc>
</teiHeader>
        
</teiCorpus>
