  <teiCorpus xmlns="http://www.tei-c.org/ns/1.0">
<teiHeader>
    <fileDesc>
                <titleStmt>
            <title>Catalogo Cicognara Number 2574</title>
        </titleStmt>
        <publicationStmt>
            <publisher>
               <orgName>Digital Cicognara Library</orgName>
               <ref>https://cicognara.org</ref>
            </publisher>
            <sectionNumber>2.3</sectionNumber>
            <idno type="cico">2574</idno>
        </publicationStmt>
        <sourceDesc>
            <bibl><author>FICORONI Francesco</author>, <title>Le memorie ritrovate nel territorio della prima e seconda città di Labico</title>, <pubPlace>Roma</pubPlace> <date>1745</date>, in 4,
fig.
<note>Opera illustrata con 18 tavole incise in rame con chiarezza e diligenza come si osserva in tutte le opere di questo
dottissimo antiquario.</note>
</bibl>
        </sourceDesc>
    </fileDesc>
</teiHeader>
        
</teiCorpus>
