  <teiCorpus xmlns="http://www.tei-c.org/ns/1.0">
<teiHeader>
    <fileDesc>
                <titleStmt>
            <title>Catalogo Cicognara Number 2740</title>
        </titleStmt>
        <publicationStmt>
            <publisher>
               <orgName>Digital Cicognara Library</orgName>
               <ref>https://cicognara.org</ref>
            </publisher>
            <sectionNumber>2.5</sectionNumber>
            <idno type="cico">2740</idno>
        </publicationStmt>
        <sourceDesc>
            <bibl><author>Bacci Andrea</author>, <title>Le dodici pietre preziose, che adornarono i vestimenti del Sommo Sacerdote</title>.
— <title>Aggiuntevi il diamante, le margherite etc. con un discorso dell’alicorno e della gran bestia detta Alce</title>, <pubPlace>Roma</pubPlace>
<date>1587</date>, in 4.
</bibl>
        </sourceDesc>
    </fileDesc>
</teiHeader>
        
</teiCorpus>
