  <teiCorpus xmlns="http://www.tei-c.org/ns/1.0">
<teiHeader>
    <fileDesc>
                <titleStmt>
            <title>Catalogo Cicognara Number 28</title>
        </titleStmt>
        <publicationStmt>
            <publisher>
               <orgName>Digital Cicognara Library</orgName>
               <ref>https://cicognara.org</ref>
            </publisher>
            <sectionNumber>1.1</sectionNumber>
            <idno type="cico">28</idno>
        </publicationStmt>
        <sourceDesc>
            <bibl>
                     <title>DIALOGUES sur les arts entre un artiste americain et un amateur français,</title> 
                     <pubPlace>Amsterdam</pubPlace> 
                     <date>1756.</date>
                  </bibl>
        </sourceDesc>
    </fileDesc>
</teiHeader>
        
</teiCorpus>
