  <teiCorpus xmlns="http://www.tei-c.org/ns/1.0">
<teiHeader>
    <fileDesc>
                <titleStmt>
            <title>Catalogo Cicognara Number 322</title>
        </titleStmt>
        <publicationStmt>
            <publisher>
               <orgName>Digital Cicognara Library</orgName>
               <ref>https://cicognara.org</ref>
            </publisher>
            <sectionNumber>1.5</sectionNumber>
            <idno type="cico">322</idno>
        </publicationStmt>
        <sourceDesc>
            <bibl>
                     <author>EUSTACHII Bartholomei</author>,
                     <title> Tabulae anatomicae editae a Jo. Maria Lancisio,</title> 
                     <pubPlace>Venetiis</pubPlace> 
                     <date>1769,</date> 
                     <extent>in fol.</extent>
	                    <note>Le pessime tavole di quest’opera non sono da osservarsi, ma si è fatto conto delle dichiarazioni che possono
	illustrare dottamente e profondamente le altre opere anatomiche per uso del disegno.</note>
                  </bibl>
        </sourceDesc>
    </fileDesc>
</teiHeader>
        
</teiCorpus>
