  <teiCorpus xmlns="http://www.tei-c.org/ns/1.0">
<teiHeader>
    <fileDesc>
                <titleStmt>
            <title>Catalogo Cicognara Number 3483</title>
        </titleStmt>
        <publicationStmt>
            <publisher>
               <orgName>Digital Cicognara Library</orgName>
               <ref>https://cicognara.org</ref>
            </publisher>
            <sectionNumber>2.9</sectionNumber>
            <idno type="cico">3483</idno>
        </publicationStmt>
        <sourceDesc>
            <bibl><author>BIAGI Clemente</author>, <title>Ragionamento sopra un’antica statua singolarissima nuovamente scoperta nell’agro romano</title>,
<pubPlace>Roma</pubPlace> <date>1771</date>, in 4, fig., M. 33.
<note>Con una tavola intagliata in rame. La statua spiegasi come rappresentante il Sole.</note>
</bibl>
        </sourceDesc>
    </fileDesc>
</teiHeader>
        
</teiCorpus>
