  <teiCorpus xmlns="http://www.tei-c.org/ns/1.0">
<teiHeader>
    <fileDesc>
                <titleStmt>
            <title>Catalogo Cicognara Number 4366</title>
        </titleStmt>
        <publicationStmt>
            <publisher>
               <orgName>Digital Cicognara Library</orgName>
               <ref>https://cicognara.org</ref>
            </publisher>
            <sectionNumber>2.19</sectionNumber>
            <idno type="cico">4366</idno>
        </publicationStmt>
        <sourceDesc>
            <bibl><author>FORMALEONI Vincenzo</author>, <title>Venezia illustrata colle vedute più cospicue, e le fabbriche più notabili rappresentate in
25 tavole con descrizione</title>, <pubPlace>Venezia</pubPlace> <date>1791</date>, in 4 oblongo.
<note>Non è da tenersi in gran pregio per l’infedeltà, e la mancanza di gusto nelle tavole, meno quelle che logore e
ritoccate riprodusse tratte dal teatro delle fabbriche più cospicue pubblicato dall’Albrizzi e intagliato da
Francesco Zucchi.</note>
</bibl>
        </sourceDesc>
    </fileDesc>
</teiHeader>
        
</teiCorpus>
