  <teiCorpus xmlns="http://www.tei-c.org/ns/1.0">
<teiHeader>
    <fileDesc>
                <titleStmt>
            <title>Catalogo Cicognara Number 446</title>
        </titleStmt>
        <publicationStmt>
            <publisher>
               <orgName>Digital Cicognara Library</orgName>
               <ref>https://cicognara.org</ref>
            </publisher>
            <sectionNumber>1.6</sectionNumber>
            <idno type="cico">446</idno>
        </publicationStmt>
        <sourceDesc>
            <bibl>
                     <author>BOSSE Abraham</author>, 
                     <title>Réprcesentation geometrale de plusieurs parties de bastimens faite par le
	regles de l’architecture antique.</title> 
                     <pubPlace>Colla data di Parigi</pubPlace> 
                     <date>1688,</date>
                     <extent> in fol. fig.</extent>
	                    <note>Opera di 22 foglietti intagliati, tutto legato in un solo volume.</note>
                  </bibl>
        </sourceDesc>
    </fileDesc>
</teiHeader>
        
</teiCorpus>
