  <teiCorpus xmlns="http://www.tei-c.org/ns/1.0">
<teiHeader>
    <fileDesc>
                <titleStmt>
            <title>Catalogo Cicognara Number 4660</title>
        </titleStmt>
        <publicationStmt>
            <publisher>
               <orgName>Digital Cicognara Library</orgName>
               <ref>https://cicognara.org</ref>
            </publisher>
            <sectionNumber>2.17</sectionNumber>
            <idno type="cico">4660</idno>
        </publicationStmt>
        <sourceDesc>
            <bibl><author>MURR (de) Cristoph. Teoph.</author>, <title>Bibliothéque de peintures, sculptures, et grâvures</title>, <pubPlace>Francfort</pubPlace> <date>1770</date>, vol. 2, in 8.
</bibl>
        </sourceDesc>
    </fileDesc>
</teiHeader>
        
</teiCorpus>
