  <teiCorpus xmlns="http://www.tei-c.org/ns/1.0">
<teiHeader>
    <fileDesc>
                <titleStmt>
            <title>Catalogo Cicognara Number 601</title>
        </titleStmt>
        <publicationStmt>
            <publisher>
               <orgName>Digital Cicognara Library</orgName>
               <ref>https://cicognara.org</ref>
            </publisher>
            <sectionNumber>1.6</sectionNumber>
            <idno type="cico">601</idno>
        </publicationStmt>
        <sourceDesc>
            <bibl> 
                     <author>PATTE</author>, 
                     <title>Mémoires sur les objets les plus importants de l’architectur,</title> 
                     <pubPlace>Paris</pubPlace> 
                     <date>1769,</date> 
                     <extent>in 4, gr. fig.</extent>
                  </bibl>
        </sourceDesc>
    </fileDesc>
</teiHeader>
        
</teiCorpus>
