  <teiCorpus xmlns="http://www.tei-c.org/ns/1.0">
<teiHeader>
    <fileDesc>
                <titleStmt>
            <title>Catalogo Cicognara Number 854</title>
        </titleStmt>
        <publicationStmt>
            <publisher>
               <orgName>Digital Cicognara Library</orgName>
               <ref>https://cicognara.org</ref>
            </publisher>
            <sectionNumber>1.9</sectionNumber>
            <idno type="cico">854</idno>
        </publicationStmt>
        <sourceDesc>
            <bibl><author>PUTEI Andreae</author>, <title>Perspectiva pictorum et architectorum</title>, <pubPlace>Roma</pubPlace> <date>1793</date>, in fol. fig. vol. 2. Latino e
	italiano.
	<note>Questa è la migliore delle varie edizioni di quest’opera, stampata in bellissimi caratteri e in carta distinta, con
	218 tavole della più nitida incisione: se il gusto veramente depravato dell’autore non rendesse ingratissima ogni
	sua produzione, sarebbe da tenersi in pregio la scienza prospettica di cui era doviziosamente fornito.</note>
	
	</bibl>
        </sourceDesc>
    </fileDesc>
</teiHeader>
        
</teiCorpus>
